restaurant_analysis/__init__.py
restaurant_analysis/data_pipeline.py
restaurant_analysis/sentiment_prediction.py
restaurant_analysis/bin/model_lr.pkl
restaurant_analysis/bin/model_pipeline.pkl
restaurant_analysis/bin/vectorizer.pkl
restaurant_analysis-0.0.1.dist-info/METADATA
restaurant_analysis-0.0.1.dist-info/WHEEL
restaurant_analysis-0.0.1.dist-info/top_level.txt
restaurant_analysis-0.0.1.dist-info/RECORD
