Metadata-Version: 2.1
Name: restaurant-analysis
Version: 0.0.1
Summary: Sentiment analysis on restaurant review
Home-page: https://github.com/rampk/restaurant-analysis
Author: Ramprakash Pavithrakannan
Author-email: UNKNOWN
License: public
Platform: UNKNOWN
